routeagent/__init__.py
routeagent/prompts.py
routeagent/router.py
routeagent-0.2.5.dist-info/LICENSE
routeagent-0.2.5.dist-info/METADATA
routeagent-0.2.5.dist-info/WHEEL
routeagent-0.2.5.dist-info/RECORD
