Metadata-Version: 2.1
Name: routeagent
Version: 0.2.5
Summary: RouteAgent is a lightweight Python library that optimizes AI task performance by intelligently routing prompts to specialized LLM agents. Building on the concept of RouteLLM, it leverages multi-agent systems to enhance accuracy in AI applications.
Author: Itachi-Uchiha581
Author-email: adeebfaiyaz@gmail.com
Requires-Python: >=3.11,<4.0
Classifier: Programming Language :: Python :: 3
Classifier: Programming Language :: Python :: 3.11
Classifier: Programming Language :: Python :: 3.12
Requires-Dist: openai (>=1.38.0,<2.0.0)
